{
  "vacinas": [
    {
      "id": 1,
      "tipo": "Vacina",
      "laboratorio": "Vacina",
      "lote": "Vacina",
      "fabricacao": "2022-04-22T14:00:00-03:00",
      "validade": "2022-04-22T14:00:00-03:00"
    },
    {
      "id": 2,
      "tipo": "Teste vacina",
      "laboratorio": "Teste vacina",
      "lote": "Teste vacina",
      "fabricacao": "2022-05-26T20:31:00-03:00",
      "validade": "2022-05-27T20:31:00-03:00"
    }
  ],
  "vacinadores": [
    {
      "id": 1,
      "nome": "Vacinador",
      "rg": "Vacinador",
      "cpf": "Vacinador",
      "endereco": "Vacinador",
      "nascimento": "2022-04-29T14:00:00-03:00"
    }
  ],
  "vacinados": [
    {
      "id": 1,
      "nome": "Teste",
      "rg": "Teste",
      "cpf": "Teste",
      "endereco": "Teste",
      "nascimento": "2022-05-06T20:21:00-03:00",
      "vacina": [],
      "vacinador": {
        "id": 1,
        "nome": "Vacinador",
        "rg": "Vacinador",
        "cpf": "Vacinador",
        "endereco": "Vacinador",
        "nascimento": "2022-04-29T14:00:00-03:00"
      }
    },
    {
      "id": 2,
      "nome": "Teste",
      "rg": "Teste",
      "cpf": "Teste",
      "endereco": "Teste",
      "nascimento": "2022-05-27T20:24:00-03:00",
      "vacina": [],
      "vacinador": {
        "id": 1,
        "nome": "Vacinador",
        "rg": "Vacinador",
        "cpf": "Vacinador",
        "endereco": "Vacinador",
        "nascimento": "2022-04-29T14:00:00-03:00"
      }
    },
    {
      "id": 3,
      "nome": "Vacinados",
      "rg": "Vacinados",
      "cpf": "Vacinados",
      "endereco": "Vacinados",
      "nascimento": "2022-05-06T20:32:00-03:00",
      "vacina": [],
      "vacinador": {
        "id": 1,
        "nome": "Vacinador",
        "rg": "Vacinador",
        "cpf": "Vacinador",
        "endereco": "Vacinador",
        "nascimento": "2022-04-29T14:00:00-03:00"
      }
    },
    {
      "id": 4,
      "nome": "Teste",
      "rg": "Teste",
      "cpf": "Teste",
      "endereco": "Teste",
      "nascimento": "2022-05-06T20:38:00-03:00",
      "vacina": [],
      "vacinador": {
        "id": 1,
        "nome": "Vacinador",
        "rg": "Vacinador",
        "cpf": "Vacinador",
        "endereco": "Vacinador",
        "nascimento": "2022-04-29T14:00:00-03:00"
      }
    },
    {
      "id": 5,
      "nome": "Vacinado1",
      "rg": "Vacinado1",
      "cpf": "Vacinado1",
      "endereco": "Vacinado1",
      "nascimento": "2022-05-04T20:44:00-03:00",
      "vacina": {
        "id": 2,
        "tipo": "Teste vacina",
        "laboratorio": "Teste vacina",
        "lote": "Teste vacina",
        "fabricacao": "2022-05-26T20:31:00-03:00",
        "validade": "2022-05-27T20:31:00-03:00"
      },
      "vacinador": {
        "id": 1,
        "nome": "Vacinador",
        "rg": "Vacinador",
        "cpf": "Vacinador",
        "endereco": "Vacinador",
        "nascimento": "2022-04-29T14:00:00-03:00"
      }
    }
  ]
}